yjviewer/__init__.py
yjviewer/locales.py
yjviewer/search.py
yjviewer/version.py
yjviewer-0.2.4.dist-info/LICENSE
yjviewer-0.2.4.dist-info/METADATA
yjviewer-0.2.4.dist-info/WHEEL
yjviewer-0.2.4.dist-info/top_level.txt
yjviewer-0.2.4.dist-info/RECORD
