Metadata-Version: 2.1
Name: yjviewer
Version: 0.2.4
Summary: A web application that lets you view YGOJSON data.
Home-page: https://github.com/iconmaster5326/YJViewer
Author: iconmaster5326
Keywords: yugioh,ygo,ygojson
Classifier: Development Status :: 3 - Alpha
Classifier: Intended Audience :: End Users/Desktop
Classifier: Topic :: Games/Entertainment
Classifier: License :: OSI Approved :: MIT License
Classifier: Programming Language :: Python :: 3
Requires-Python: >=3.8, <4
License-File: LICENSE
Requires-Dist: Flask
Requires-Dist: lark
Requires-Dist: ygojson
Provides-Extra: dev
Requires-Dist: pre-commit ; extra == 'dev'
Requires-Dist: watchdog ; extra == 'dev'
Provides-Extra: test
